<?xml version="1.0" encoding="utf-8"?>
<resources>
  <dimen name="Size_18" defaultValue="18">6dp</dimen>
  <dimen name="Size_36" defaultValue="36">12dp</dimen>
  <dimen name="Size_54" defaultValue="54">18dp</dimen>
  <dimen name="Size_66" defaultValue="66">22dp</dimen>
  <dimen name="Size_72" defaultValue="72">24dp</dimen>
  <dimen name="Size_90" defaultValue="90">30dp</dimen>
  <dimen name="Size_96" defaultValue="96">32dp</dimen>
  <dimen name="Size_102" defaultValue="102">34dp</dimen>
  <dimen name="Size_126" defaultValue="126">42dp</dimen>
  <dimen name="Size_132" defaultValue="132">44dp</dimen>
  <dimen name="Size_144" defaultValue="144">48dp</dimen>
  <dimen name="Size_150" defaultValue="150">50dp</dimen>
  <dimen name="Size_180" defaultValue="180">60dp</dimen>
  <dimen name="Size_204" defaultValue="204">68dp</dimen>
  <dimen name="Size_216" defaultValue="216">72dp</dimen>
  <dimen name="Size_222" defaultValue="222">74dp</dimen>
  <dimen name="Size_240" defaultValue="240">80dp</dimen>
  <dimen name="Size_246" defaultValue="246">82dp</dimen>
  <dimen name="Size_252" defaultValue="252">84dp</dimen>
  <dimen name="Size_270" defaultValue="270">90dp</dimen>
  <dimen name="Size_282" defaultValue="282">94dp</dimen>
  <dimen name="Size_318" defaultValue="318">106dp</dimen>
  <dimen name="Size_324" defaultValue="324">108dp</dimen>
  <dimen name="Size_450" defaultValue="450">150dp</dimen>
  <dimen name="Size_468" defaultValue="468">156dp</dimen>
  <dimen name="Size_480" defaultValue="480">160dp</dimen>
  <dimen name="Size_504" defaultValue="504">168dp</dimen>
  <dimen name="Size_552" defaultValue="552">184dp</dimen>
  <dimen name="Size_690" defaultValue="690">230dp</dimen>
  <dimen name="Size_756" defaultValue="756">252dp</dimen>
  <dimen name="Size_810" defaultValue="810">270dp</dimen>
  <dimen name="Size_864" defaultValue="864">288dp</dimen>
  <dimen name="Size_948" defaultValue="948">316dp</dimen>
  <dimen name="Size_1212" defaultValue="1212">404dp</dimen>
  <dimen name="Size_1254" defaultValue="1254">418dp</dimen>
  <dimen name="Padding_12" defaultValue="12">4dp</dimen>
  <dimen name="Padding_30" defaultValue="30">10dp</dimen>
  <dimen name="Padding_42" defaultValue="42">14dp</dimen>
  <dimen name="Padding_78" defaultValue="78">26dp</dimen>
  <dimen name="Padding_66" defaultValue="66">22dp</dimen>
  <dimen name="Padding_120" defaultValue="120">40dp</dimen>
  <dimen name="Padding_174" defaultValue="174">58dp</dimen>
  
  <!--ProductDetail页面  图片  宽和高-->
  <dimen name="ProductD_Pic_W" defaultValue="1080">360dp</dimen>
  <dimen name="ProductD_Pic_H" defaultValue="1080">360dp</dimen>
  
</resources>